pelican_diminuendo/__init__.py
pelican_diminuendo-0.2.1.dist-info/WHEEL
pelican_diminuendo-0.2.1.dist-info/metadata.json
pelican_diminuendo-0.2.1.dist-info/DESCRIPTION.rst
pelican_diminuendo-0.2.1.dist-info/top_level.txt
pelican_diminuendo-0.2.1.dist-info/RECORD
pelican_diminuendo-0.2.1.dist-info/METADATA
pelican-diminuendo/__init__.py
