Metadata-Version: 2.0
Name: pelican-diminuendo
Version: 0.2.1
Summary: HTML minifier plugin for Pelican
Home-page: https://github.com/hrbonz/pelican-diminuendo
Author: Stefan "hr" Berder
Author-email: hr@bonz.org
License: BSD 3-Clause
Keywords: pelican minify
Platform: UNKNOWN
Classifier: Development Status :: 3 - Alpha
Classifier: Environment :: Console
Classifier: Intended Audience :: Developers
Classifier: License :: OSI Approved :: BSD License
Classifier: Programming Language :: Python :: 2.7
Classifier: Programming Language :: Python :: 3.3
Classifier: Topic :: Internet
Requires-Dist: pelican
Requires-Dist: python-diminuendo
